term_math/__init__.py
term_math/calculate.py
term_math-0.2.0.dist-info/LICENSE
term_math-0.2.0.dist-info/METADATA
term_math-0.2.0.dist-info/WHEEL
term_math-0.2.0.dist-info/top_level.txt
term_math-0.2.0.dist-info/RECORD
