Metadata-Version: 2.1
Name: term-math
Version: 0.2.0
Summary: Add, subtract, multiply, divide with terminal
Home-page: https://github.com/bgala/term_math
Author: Bhavin Gala
Author-email: bhavinpgala@gmail.com
License: MIT License
Platform: UNKNOWN
